whochat/__init__.py
whochat/__main__.py
whochat/_comtypes.py
whochat/abc.py
whochat/bot.py
whochat/cli.py
whochat/logger.py
whochat/settings.py
whochat/signals.py
whochat/utils.py
whochat/ComWeChatRobot/CWeChatRobot.exe
whochat/ComWeChatRobot/DWeChatRobot.dll
whochat/ComWeChatRobot/__init__.py
whochat/messages/__init__.py
whochat/messages/constants.py
whochat/messages/tcp.py
whochat/messages/websocket.py
whochat/rpc/__init__.py
whochat/rpc/docs.py
whochat/rpc/handlers.py
whochat/rpc/clients/__init__.py
whochat/rpc/clients/websocket.py
whochat/rpc/servers/__init__.py
whochat/rpc/servers/http.py
whochat/rpc/servers/websocket.py
whochat-1.3.5.dist-info/LICENSE
whochat-1.3.5.dist-info/METADATA
whochat-1.3.5.dist-info/WHEEL
whochat-1.3.5.dist-info/entry_points.txt
whochat-1.3.5.dist-info/top_level.txt
whochat-1.3.5.dist-info/RECORD
