Metadata-Version: 2.1
Name: whochat
Version: 1.3.5
Summary: 一个命令就可启用的微信机器人
Home-page: https://github.com/amchii/whochat
Author: Amchii
Author-email: finethankuandyou@gmail.com
License: BSD 3-Clause License
Project-URL: Source, https://github.com/amchii/whochat
Classifier: Intended Audience :: Developers
Classifier: Operating System :: Microsoft :: Windows
Classifier: License :: OSI Approved :: BSD License
Classifier: Programming Language :: Python :: 3 :: Only
Classifier: Programming Language :: Python :: 3.8
Requires-Python: >=3.8
License-File: LICENSE
Requires-Dist: comtypes
Requires-Dist: psutil
Requires-Dist: click
Requires-Dist: websockets
Requires-Dist: jsonrpcserver
Requires-Dist: jsonrpcclient
Requires-Dist: schedule
Requires-Dist: pydantic[dotenv]
Provides-Extra: httprpc
Requires-Dist: fastapi[uvicorn] ; extra == 'httprpc'
